udar/__init__.py
udar/__main__.py
udar/convenience.py
udar/document.py
udar/fsts.py
udar/misc.py
udar/reading.py
udar/sentence.py
udar/subreading.py
udar/tag.py
udar/tok.py
udar/transliterate.py
udar/version.py
udar/conversion/OC_conflicts.py
udar/conversion/OC_tags.py
udar/conversion/UD_conflicts.py
udar/conversion/__init__.py
udar/conversion/external2udar.py
udar/experiments/__init__.py
udar/experiments/stress_experiment.py
udar/experiments/stress_corpus/anna_karenina.ref
udar/experiments/stress_corpus/anna_karenina2.ref
udar/experiments/stress_corpus/dialogs.ref
udar/experiments/stress_corpus/difficult-talk.ref
udar/experiments/stress_corpus/matryoshka.ref
udar/experiments/stress_corpus/meaning-of-life.ref
udar/experiments/stress_corpus/nervous-buyer.ref
udar/experiments/stress_corpus/pilot-doctor1.ref
udar/experiments/stress_corpus/pilot-doctor2.ref
udar/experiments/stress_corpus/robot.ref
udar/experiments/stress_corpus/salesperson.ref
udar/experiments/stress_corpus/sample-first-russian-reader.ref
udar/experiments/stress_corpus/shady.ref
udar/experiments/stress_corpus/too-different.ref
udar/features/__init__.py
udar/features/absolute_length.py
udar/features/discourse.py
udar/features/feature.py
udar/features/feature_extractor.py
udar/features/features.py
udar/features/lexical_complexity.py
udar/features/lexical_familiarity.py
udar/features/lexical_variability.py
udar/features/morphology.py
udar/features/normalized_length.py
udar/features/priors.py
udar/features/readability.py
udar/features/sentence.py
udar/features/syntax.py
udar/resources/RNC_tok_freq_dict.pkl
udar/resources/RNC_tok_freq_rank_dict.pkl
udar/resources/Sharoff_lem_freq_dict.pkl
udar/resources/Sharoff_lem_freq_rank_dict.pkl
udar/resources/Tix_morph_count_dict.pkl
udar/resources/Tixonov_dict.pkl
udar/resources/analyser-gt-desc-L2.hfstol.gz
udar/resources/analyser-gt-desc.hfstol.gz
udar/resources/disambiguator.cg3
udar/resources/g2p.hfstol.gz
udar/resources/generator-gt-norm.accented.hfstol.gz
udar-0.1.10.dist-info/LICENSE
udar-0.1.10.dist-info/METADATA
udar-0.1.10.dist-info/WHEEL
udar-0.1.10.dist-info/top_level.txt
udar-0.1.10.dist-info/RECORD
